{
  "date": "2026-07-03",
  "vectors": [
    {
      "lat": 10,
      "lon": -16,
      "u10": -4.99,
      "v10": -1.57
    },
    {
      "lat": 10,
      "lon": -14,
      "u10": -4.63,
      "v10": -1.97
    },
    {
      "lat": 10,
      "lon": -12,
      "u10": -3.78,
      "v10": -2.26
    },
    {
      "lat": 10,
      "lon": -10,
      "u10": -3.56,
      "v10": -1.81
    },
    {
      "lat": 10,
      "lon": -8,
      "u10": -3.32,
      "v10": -1.19
    },
    {
      "lat": 10,
      "lon": -6,
      "u10": -3.34,
      "v10": -2.94
    },
    {
      "lat": 10,
      "lon": -4,
      "u10": -3.02,
      "v10": -1.73
    },
    {
      "lat": 10,
      "lon": -2,
      "u10": -4.27,
      "v10": -1.26
    },
    {
      "lat": 10,
      "lon": 0,
      "u10": -4.57,
      "v10": -2.25
    },
    {
      "lat": 10,
      "lon": 2,
      "u10": -3.44,
      "v10": -1.07
    },
    {
      "lat": 10,
      "lon": 4,
      "u10": -4.74,
      "v10": -2.83
    },
    {
      "lat": 10,
      "lon": 6,
      "u10": -3.92,
      "v10": -2.02
    },
    {
      "lat": 10,
      "lon": 8,
      "u10": -3.75,
      "v10": -2.41
    },
    {
      "lat": 10,
      "lon": 10,
      "u10": -4.53,
      "v10": -2.15
    },
    {
      "lat": 10,
      "lon": 12,
      "u10": -4.42,
      "v10": -2.45
    },
    {
      "lat": 10,
      "lon": 14,
      "u10": -4.88,
      "v10": -1.14
    },
    {
      "lat": 10,
      "lon": 16,
      "u10": -4.85,
      "v10": -1.08
    },
    {
      "lat": 10,
      "lon": 18,
      "u10": -4.81,
      "v10": -2.13
    },
    {
      "lat": 10,
      "lon": 20,
      "u10": -4.32,
      "v10": -1.72
    },
    {
      "lat": 10,
      "lon": 22,
      "u10": -3.18,
      "v10": -1.98
    },
    {
      "lat": 10,
      "lon": 24,
      "u10": -4.36,
      "v10": -2.82
    },
    {
      "lat": 12,
      "lon": -16,
      "u10": -4.06,
      "v10": -1.19
    },
    {
      "lat": 12,
      "lon": -14,
      "u10": -4.87,
      "v10": -2.43
    },
    {
      "lat": 12,
      "lon": -12,
      "u10": -3.46,
      "v10": -1.97
    },
    {
      "lat": 12,
      "lon": -10,
      "u10": -3.2,
      "v10": -1.24
    },
    {
      "lat": 12,
      "lon": -8,
      "u10": -4.26,
      "v10": -2.3
    },
    {
      "lat": 12,
      "lon": -6,
      "u10": -4.89,
      "v10": -2.71
    },
    {
      "lat": 12,
      "lon": -4,
      "u10": -4.87,
      "v10": -1.85
    },
    {
      "lat": 12,
      "lon": -2,
      "u10": -4.32,
      "v10": -1.26
    },
    {
      "lat": 12,
      "lon": 0,
      "u10": -4.14,
      "v10": -2.2
    },
    {
      "lat": 12,
      "lon": 2,
      "u10": -3.31,
      "v10": -1.86
    },
    {
      "lat": 12,
      "lon": 4,
      "u10": -4.49,
      "v10": -2.58
    },
    {
      "lat": 12,
      "lon": 6,
      "u10": -4.17,
      "v10": -1.84
    },
    {
      "lat": 12,
      "lon": 8,
      "u10": -4.66,
      "v10": -1.93
    },
    {
      "lat": 12,
      "lon": 10,
      "u10": -4.34,
      "v10": -1.22
    },
    {
      "lat": 12,
      "lon": 12,
      "u10": -4.2,
      "v10": -2.61
    },
    {
      "lat": 12,
      "lon": 14,
      "u10": -4.24,
      "v10": -2.9
    },
    {
      "lat": 12,
      "lon": 16,
      "u10": -3.21,
      "v10": -1.39
    },
    {
      "lat": 12,
      "lon": 18,
      "u10": -4.05,
      "v10": -2.1
    },
    {
      "lat": 12,
      "lon": 20,
      "u10": -3.92,
      "v10": -2.05
    },
    {
      "lat": 12,
      "lon": 22,
      "u10": -4.6,
      "v10": -2.58
    },
    {
      "lat": 12,
      "lon": 24,
      "u10": -4.97,
      "v10": -2.91
    },
    {
      "lat": 14,
      "lon": -16,
      "u10": -4.67,
      "v10": -1.84
    },
    {
      "lat": 14,
      "lon": -14,
      "u10": -4.65,
      "v10": -2.93
    },
    {
      "lat": 14,
      "lon": -12,
      "u10": -3.62,
      "v10": -1.58
    },
    {
      "lat": 14,
      "lon": -10,
      "u10": -4.09,
      "v10": -1.02
    },
    {
      "lat": 14,
      "lon": -8,
      "u10": -4.25,
      "v10": -1.92
    },
    {
      "lat": 14,
      "lon": -6,
      "u10": -3.49,
      "v10": -1.96
    },
    {
      "lat": 14,
      "lon": -4,
      "u10": -4.88,
      "v10": -1.04
    },
    {
      "lat": 14,
      "lon": -2,
      "u10": -3.06,
      "v10": -1.11
    },
    {
      "lat": 14,
      "lon": 0,
      "u10": -4.62,
      "v10": -1.45
    },
    {
      "lat": 14,
      "lon": 2,
      "u10": -4.73,
      "v10": -2.42
    },
    {
      "lat": 14,
      "lon": 4,
      "u10": -4.37,
      "v10": -1.6
    },
    {
      "lat": 14,
      "lon": 6,
      "u10": -3.47,
      "v10": -1.45
    },
    {
      "lat": 14,
      "lon": 8,
      "u10": -3.86,
      "v10": -2.73
    },
    {
      "lat": 14,
      "lon": 10,
      "u10": -3.71,
      "v10": -2.94
    },
    {
      "lat": 14,
      "lon": 12,
      "u10": -4.99,
      "v10": -1.12
    },
    {
      "lat": 14,
      "lon": 14,
      "u10": -3.17,
      "v10": -2.44
    },
    {
      "lat": 14,
      "lon": 16,
      "u10": -3.5,
      "v10": -1.31
    },
    {
      "lat": 14,
      "lon": 18,
      "u10": -3.09,
      "v10": -2.83
    },
    {
      "lat": 14,
      "lon": 20,
      "u10": -3.63,
      "v10": -1.07
    },
    {
      "lat": 14,
      "lon": 22,
      "u10": -3.59,
      "v10": -2.36
    },
    {
      "lat": 14,
      "lon": 24,
      "u10": -4.47,
      "v10": -2.64
    },
    {
      "lat": 16,
      "lon": -16,
      "u10": -3.55,
      "v10": -2.46
    },
    {
      "lat": 16,
      "lon": -14,
      "u10": -3.5,
      "v10": -2.28
    },
    {
      "lat": 16,
      "lon": -12,
      "u10": -3.38,
      "v10": -2.26
    },
    {
      "lat": 16,
      "lon": -10,
      "u10": -4.22,
      "v10": -2.99
    },
    {
      "lat": 16,
      "lon": -8,
      "u10": -4.71,
      "v10": -2.54
    },
    {
      "lat": 16,
      "lon": -6,
      "u10": -3.29,
      "v10": -1.4
    },
    {
      "lat": 16,
      "lon": -4,
      "u10": -3.96,
      "v10": -2.43
    },
    {
      "lat": 16,
      "lon": -2,
      "u10": -4.64,
      "v10": -1.66
    },
    {
      "lat": 16,
      "lon": 0,
      "u10": -3.22,
      "v10": -2.7
    },
    {
      "lat": 16,
      "lon": 2,
      "u10": -3.97,
      "v10": -2.64
    },
    {
      "lat": 16,
      "lon": 4,
      "u10": -3.89,
      "v10": -1.28
    },
    {
      "lat": 16,
      "lon": 6,
      "u10": -4.58,
      "v10": -2.05
    },
    {
      "lat": 16,
      "lon": 8,
      "u10": -3.86,
      "v10": -1.2
    },
    {
      "lat": 16,
      "lon": 10,
      "u10": -3.83,
      "v10": -2.08
    },
    {
      "lat": 16,
      "lon": 12,
      "u10": -4.33,
      "v10": -2.15
    },
    {
      "lat": 16,
      "lon": 14,
      "u10": -3.05,
      "v10": -1.18
    },
    {
      "lat": 16,
      "lon": 16,
      "u10": -4.82,
      "v10": -2.71
    },
    {
      "lat": 16,
      "lon": 18,
      "u10": -3.45,
      "v10": -1.77
    },
    {
      "lat": 16,
      "lon": 20,
      "u10": -4.74,
      "v10": -2.11
    },
    {
      "lat": 16,
      "lon": 22,
      "u10": -4.77,
      "v10": -2.7
    },
    {
      "lat": 16,
      "lon": 24,
      "u10": -4.5,
      "v10": -1.66
    },
    {
      "lat": 18,
      "lon": -16,
      "u10": -4.66,
      "v10": -2.88
    },
    {
      "lat": 18,
      "lon": -14,
      "u10": -3.97,
      "v10": -2.9
    },
    {
      "lat": 18,
      "lon": -12,
      "u10": -4.29,
      "v10": -2.74
    },
    {
      "lat": 18,
      "lon": -10,
      "u10": -4.27,
      "v10": -1.97
    },
    {
      "lat": 18,
      "lon": -8,
      "u10": -3.53,
      "v10": -1.52
    },
    {
      "lat": 18,
      "lon": -6,
      "u10": -3.34,
      "v10": -1.77
    },
    {
      "lat": 18,
      "lon": -4,
      "u10": -3.94,
      "v10": -1.19
    },
    {
      "lat": 18,
      "lon": -2,
      "u10": -4.04,
      "v10": -2.62
    },
    {
      "lat": 18,
      "lon": 0,
      "u10": -4.73,
      "v10": -2.48
    },
    {
      "lat": 18,
      "lon": 2,
      "u10": -4.98,
      "v10": -2.46
    },
    {
      "lat": 18,
      "lon": 4,
      "u10": -4.86,
      "v10": -1.06
    },
    {
      "lat": 18,
      "lon": 6,
      "u10": -3.65,
      "v10": -2.23
    },
    {
      "lat": 18,
      "lon": 8,
      "u10": -4.95,
      "v10": -2.25
    },
    {
      "lat": 18,
      "lon": 10,
      "u10": -4.36,
      "v10": -1.89
    },
    {
      "lat": 18,
      "lon": 12,
      "u10": -4.25,
      "v10": -2.21
    },
    {
      "lat": 18,
      "lon": 14,
      "u10": -3.92,
      "v10": -2.14
    },
    {
      "lat": 18,
      "lon": 16,
      "u10": -4.32,
      "v10": -1.29
    },
    {
      "lat": 18,
      "lon": 18,
      "u10": -3.6,
      "v10": -2.78
    },
    {
      "lat": 18,
      "lon": 20,
      "u10": -3.96,
      "v10": -2.34
    },
    {
      "lat": 18,
      "lon": 22,
      "u10": -4.48,
      "v10": -2.6
    },
    {
      "lat": 18,
      "lon": 24,
      "u10": -3.5,
      "v10": -2.66
    },
    {
      "lat": 20,
      "lon": -16,
      "u10": -3.85,
      "v10": -1.22
    },
    {
      "lat": 20,
      "lon": -14,
      "u10": -3.12,
      "v10": -2.01
    },
    {
      "lat": 20,
      "lon": -12,
      "u10": -3.52,
      "v10": -2.03
    },
    {
      "lat": 20,
      "lon": -10,
      "u10": -3.38,
      "v10": -2.38
    },
    {
      "lat": 20,
      "lon": -8,
      "u10": -4.41,
      "v10": -1.31
    },
    {
      "lat": 20,
      "lon": -6,
      "u10": -4.47,
      "v10": -2.61
    },
    {
      "lat": 20,
      "lon": -4,
      "u10": -4.67,
      "v10": -2.94
    },
    {
      "lat": 20,
      "lon": -2,
      "u10": -4.55,
      "v10": -1.56
    },
    {
      "lat": 20,
      "lon": 0,
      "u10": -4.52,
      "v10": -2.19
    },
    {
      "lat": 20,
      "lon": 2,
      "u10": -4.31,
      "v10": -1.7
    },
    {
      "lat": 20,
      "lon": 4,
      "u10": -3.36,
      "v10": -1.94
    },
    {
      "lat": 20,
      "lon": 6,
      "u10": -3.07,
      "v10": -2.87
    },
    {
      "lat": 20,
      "lon": 8,
      "u10": -3.41,
      "v10": -1.08
    },
    {
      "lat": 20,
      "lon": 10,
      "u10": -4.16,
      "v10": -2.32
    },
    {
      "lat": 20,
      "lon": 12,
      "u10": -4.33,
      "v10": -2.35
    },
    {
      "lat": 20,
      "lon": 14,
      "u10": -3.61,
      "v10": -1.47
    },
    {
      "lat": 20,
      "lon": 16,
      "u10": -3.88,
      "v10": -2.65
    },
    {
      "lat": 20,
      "lon": 18,
      "u10": -4.18,
      "v10": -2.71
    },
    {
      "lat": 20,
      "lon": 20,
      "u10": -4,
      "v10": -2.51
    },
    {
      "lat": 20,
      "lon": 22,
      "u10": -4.77,
      "v10": -2.83
    },
    {
      "lat": 20,
      "lon": 24,
      "u10": -4.32,
      "v10": -2
    }
  ]
}